[
  {
    "title": "frontend",
    "skill": [
      { "id": 1, "name": "html/css", "progress": 80 },
      { "id": 2, "name": "javascript", "progress": 85 },
      { "id": 3, "name": "react", "progress": 90 },
      { "id": 4, "name": "redux", "progress": 70 },
      { "id": 5, "name": "tailwind", "progress": 80 },
      { "id": 52, "name": "sass", "progress": 80 },
      { "id": 6, "name": "gatsby", "progress": 70 },
      { "id": 7, "name": "typescript", "progress": 80 }
    ]
  },
  {
    "title": "backend",
    "skill": [
      { "id": 23, "name": "firebase", "progress": 80 },
      { "id": 231, "name": "node.js", "progress": 70 },
      { "id": 8, "name": "express", "progress": 60 },
      { "id": 9, "name": "next.js", "progress": 70 },
      { "id": 10, "name": "graphql", "progress": 70 },
      { "id": 11, "name": "java", "progress": 70 },
      { "id": 13, "name": "python", "progress": 70 }
    ]
  },
  {
    "title": "others",
    "skill": [
      { "id": 13, "name": "git", "progress": 70 },
      { "id": 14, "name": "github", "progress": 70 }      
    ]
  }
]
